{
  "entityType" : "DEVICE",
  "entity" : {
    "additionalInfo" : {
      "gateway" : false,
      "overwriteActivityTime" : false,
      "description" : ""
    },
    "customerId" : {
      "entityType" : "CUSTOMER",
      "id" : "2893cc90-588a-11ee-9f7b-8198b0245bf9"
    },
    "deviceData" : {
      "configuration" : {
        "type" : "DEFAULT"
      },
      "transportConfiguration" : {
        "type" : "DEFAULT"
      }
    },
    "deviceProfileId" : {
      "entityType" : "DEVICE_PROFILE",
      "id" : "165d6970-4362-11ed-b66e-bd8d8d68617d"
    },
    "externalId" : null,
    "firmwareId" : null,
    "id" : {
      "entityType" : "DEVICE",
      "id" : "4e5abfe0-498d-11ed-b66e-bd8d8d68617d"
    },
    "label" : "L.WHIRLPOOL-300",
    "name" : "300_001-202105-PH",
    "softwareId" : null,
    "type" : "ECOPRO"
  },
  "credentials" : {
    "credentialsId" : "300.001-202105-PH",
    "credentialsType" : "ACCESS_TOKEN",
    "credentialsValue" : null
  },
  "attributes" : {
    "SERVER_SCOPE" : [ {
      "booleanValue" : null,
      "doubleValue" : null,
      "jsonValue" : null,
      "key" : "Alto Fluxo de águaRepeatCount",
      "lastUpdateTs" : 1695164645850,
      "longValue" : 0,
      "strValue" : null
    }, {
      "booleanValue" : null,
      "doubleValue" : null,
      "jsonValue" : null,
      "key" : "Connectivity AlarmRepeatCount",
      "lastUpdateTs" : 1695150113650,
      "longValue" : 0,
      "strValue" : null
    }, {
      "booleanValue" : null,
      "doubleValue" : null,
      "jsonValue" : null,
      "key" : "Fluxo de águaRepeatCount",
      "lastUpdateTs" : 1695150542292,
      "longValue" : 0,
      "strValue" : null
    }, {
      "booleanValue" : false,
      "doubleValue" : null,
      "jsonValue" : null,
      "key" : "Inoperante",
      "lastUpdateTs" : 1700234137000,
      "longValue" : null,
      "strValue" : null
    }, {
      "booleanValue" : true,
      "doubleValue" : null,
      "jsonValue" : null,
      "key" : "Moldem - Eco",
      "lastUpdateTs" : 1782395877608,
      "longValue" : null,
      "strValue" : null
    }, {
      "booleanValue" : null,
      "doubleValue" : null,
      "jsonValue" : null,
      "key" : "Peso aumentando com porta fechadaRepeatCount",
      "lastUpdateTs" : 1692643305543,
      "longValue" : 0,
      "strValue" : null
    }, {
      "booleanValue" : null,
      "doubleValue" : null,
      "jsonValue" : null,
      "key" : "PesoRepeatCount",
      "lastUpdateTs" : 1695243299864,
      "longValue" : 0,
      "strValue" : null
    }, {
      "booleanValue" : null,
      "doubleValue" : null,
      "jsonValue" : null,
      "key" : "Porta AbertaRepeatCount",
      "lastUpdateTs" : 1694701059194,
      "longValue" : 0,
      "strValue" : null
    }, {
      "booleanValue" : null,
      "doubleValue" : null,
      "jsonValue" : null,
      "key" : "Sobrepeso ServersideRepeatCount",
      "lastUpdateTs" : 1695157283881,
      "longValue" : 0,
      "strValue" : null
    }, {
      "booleanValue" : false,
      "doubleValue" : null,
      "jsonValue" : null,
      "key" : "active",
      "lastUpdateTs" : 1782824657811,
      "longValue" : null,
      "strValue" : null
    }, {
      "booleanValue" : null,
      "doubleValue" : 635.1745366063739,
      "jsonValue" : null,
      "key" : "calibration_kg",
      "lastUpdateTs" : 1695303509163,
      "longValue" : null,
      "strValue" : null
    }, {
      "booleanValue" : null,
      "doubleValue" : null,
      "jsonValue" : null,
      "key" : "clientEmail",
      "lastUpdateTs" : 1781026096623,
      "longValue" : null,
      "strValue" : ""
    }, {
      "booleanValue" : null,
      "doubleValue" : null,
      "jsonValue" : null,
      "key" : "clientName",
      "lastUpdateTs" : 1781026096623,
      "longValue" : null,
      "strValue" : ""
    }, {
      "booleanValue" : null,
      "doubleValue" : null,
      "jsonValue" : null,
      "key" : "connectionType",
      "lastUpdateTs" : 1781026096623,
      "longValue" : null,
      "strValue" : "CLIENT"
    }, {
      "booleanValue" : false,
      "doubleValue" : null,
      "jsonValue" : null,
      "key" : "criticalAsset",
      "lastUpdateTs" : 1781026096623,
      "longValue" : null,
      "strValue" : null
    }, {
      "booleanValue" : null,
      "doubleValue" : null,
      "jsonValue" : "{\"emailAlerta\":\"renata.pioalves@projefood.com.br\"}",
      "key" : "emailAlerta",
      "lastUpdateTs" : 1744765548184,
      "longValue" : null,
      "strValue" : null
    }, {
      "booleanValue" : null,
      "doubleValue" : null,
      "jsonValue" : null,
      "key" : "inactivityAlarmTime",
      "lastUpdateTs" : 1782824657811,
      "longValue" : 1782824657811,
      "strValue" : null
    }, {
      "booleanValue" : null,
      "doubleValue" : null,
      "jsonValue" : null,
      "key" : "inactivityTimeout",
      "lastUpdateTs" : 1725549666608,
      "longValue" : 3000,
      "strValue" : null
    }, {
      "booleanValue" : null,
      "doubleValue" : null,
      "jsonValue" : null,
      "key" : "lastActivityTime",
      "lastUpdateTs" : 1782824618620,
      "longValue" : 1782824616226,
      "strValue" : null
    }, {
      "booleanValue" : null,
      "doubleValue" : 635.2499999999999,
      "jsonValue" : null,
      "key" : "lastCalibration_kg",
      "lastUpdateTs" : 1695303509163,
      "longValue" : null,
      "strValue" : null
    }, {
      "booleanValue" : null,
      "doubleValue" : null,
      "jsonValue" : null,
      "key" : "lastConnectTime",
      "lastUpdateTs" : 1725287406568,
      "longValue" : 1725287406566,
      "strValue" : null
    }, {
      "booleanValue" : null,
      "doubleValue" : null,
      "jsonValue" : null,
      "key" : "lastDisconnectTime",
      "lastUpdateTs" : 1725287406687,
      "longValue" : 1725287406687,
      "strValue" : null
    }, {
      "booleanValue" : null,
      "doubleValue" : null,
      "jsonValue" : null,
      "key" : "lastDoorOpenTimestamp",
      "lastUpdateTs" : 1695298424113,
      "longValue" : 1695298423000,
      "strValue" : null
    }, {
      "booleanValue" : null,
      "doubleValue" : null,
      "jsonValue" : null,
      "key" : "n2NotifiedTs",
      "lastUpdateTs" : 1781019886957,
      "longValue" : null,
      "strValue" : "epoch ms "
    }, {
      "booleanValue" : null,
      "doubleValue" : null,
      "jsonValue" : null,
      "key" : "n3NotifiedTs",
      "lastUpdateTs" : 1781019886957,
      "longValue" : null,
      "strValue" : "epoch ms "
    }, {
      "booleanValue" : null,
      "doubleValue" : null,
      "jsonValue" : null,
      "key" : "offlineSince",
      "lastUpdateTs" : 1781019886957,
      "longValue" : null,
      "strValue" : "epoch ms "
    }, {
      "booleanValue" : null,
      "doubleValue" : null,
      "jsonValue" : null,
      "key" : "siteLocation",
      "lastUpdateTs" : 1781026096623,
      "longValue" : null,
      "strValue" : ""
    }, {
      "booleanValue" : null,
      "doubleValue" : null,
      "jsonValue" : null,
      "key" : "slaLavel",
      "lastUpdateTs" : 1781019886957,
      "longValue" : 0,
      "strValue" : null
    }, {
      "booleanValue" : null,
      "doubleValue" : null,
      "jsonValue" : null,
      "key" : "ultimoEnvioEmail",
      "lastUpdateTs" : 1782824560009,
      "longValue" : 1782824560009,
      "strValue" : null
    } ],
    "SHARED_SCOPE" : [ ]
  }
}